logtail/__init__.py
logtail/cli.py
logtail/logtail.py
logtail/utils.py
logtail-1.0.0.dist-info/METADATA
logtail-1.0.0.dist-info/RECORD
logtail-1.0.0.dist-info/WHEEL
logtail-1.0.0.dist-info/entry_points.txt
logtail-1.0.0.dist-info/top_level.txt
