Metadata-Version: 2.1
Name: logtail
Version: 1.0.0
Summary: Package for tailing logs and viewing in editor
Home-page: http://github.com/bucknerns
Author: Nathan Buckner
Author-email: nathan.buckner@rackspace.com
License: Apache License
